distortion/__init__.py
distortion/distortion.py
distortion/distortion_test.py
distortion-0.1.31.dist-info/LICENSE
distortion-0.1.31.dist-info/WHEEL
distortion-0.1.31.dist-info/METADATA
distortion-0.1.31.dist-info/RECORD
