Metadata-Version: 2.1
Name: distortion
Version: 0.1.31
Summary: Watermark distortions
Home-page: https://github.com/tanimutomo/watermark-distortions
License: Apache-2.0
Author: tanimutomo
Author-email: tanimutomo@gmail.com
Requires-Python: >=3.8,<4.0
Classifier: License :: OSI Approved :: Apache Software License
Classifier: Programming Language :: Python :: 3
Classifier: Programming Language :: Python :: 3.8
Classifier: Programming Language :: Python :: 3.9
Requires-Dist: kornia (>=0.5.0,<0.6.0)
Requires-Dist: torch (>=1.6.0,<2.0.0)
Project-URL: Repository, https://github.com/tanimutomo/watermark-distortions
